ansi/__init__.py
ansi/color.py
ansi/cursor.py
ansi/iterm.py
ansi/osc.py
ansi/py.typed
ansi/sequence.py
ansi/colour/__init__.py
ansi/colour/base.py
ansi/colour/bg.py
ansi/colour/fg.py
ansi/colour/fx.py
ansi/colour/rgb.py
ansi-0.3.7.dist-info/LICENSE.md
ansi-0.3.7.dist-info/METADATA
ansi-0.3.7.dist-info/WHEEL
ansi-0.3.7.dist-info/top_level.txt
ansi-0.3.7.dist-info/RECORD
