Metadata-Version: 2.1
Name: ansi
Version: 0.3.7
Summary: ANSI cursor movement and graphics
Home-page: https://github.com/tehmaze/ansi/
Author: Wijnand Modderman-Lenstra
Author-email: maze@pyth0n.org
License: MIT License
Requires-Python: >=3.6
License-File: LICENSE.md
Requires-Dist: typing_extensions>=3.6.4; python_version < "3.8"
